{
  "title": "Mario Kart DS - Retro Tracks",
  "attempt_count": 1,
  "start_delay": "3.000000",
  "splits": [
    {
      "title": "SNES Mario Circuit 1",
      "time": "1:09.620903",
      "best_time": "1:09.620903",
      "best_segment": "1:09.620903"
    },
    {
      "title": "N64 Moo Moo Farm",
      "time": "2:50.320407",
      "best_time": "2:50.320407",
      "best_segment": "1:40.699504"
    },
    {
      "title": "GBA Peach Circuit",
      "time": "4:16.989187",
      "best_time": "4:16.989187",
      "best_segment": "1:26.668780"
    },
    {
      "title": "GCN Luigi Circuit",
      "time": "6:06.966704",
      "best_time": "6:06.966704",
      "best_segment": "1:49.977517"
    },
    {
      "title": "SNES Donut Plains 1",
      "time": "7:31.401921",
      "best_time": "7:31.401921",
      "best_segment": "1:24.435217"
    },
    {
      "title": "N64 Frappe Snowland",
      "time": "10:06.942239",
      "best_time": "10:06.942239",
      "best_segment": "2:35.540318"
    },
    {
      "title": "GBA Bowser Castle 2",
      "time": "12:31.670006",
      "best_time": "12:31.670006",
      "best_segment": "2:24.727767"
    },
    {
      "title": "GCN Baby Park",
      "time": "13:46.664448",
      "best_time": "13:46.664448",
      "best_segment": "1:14.994442"
    },
    {
      "title": "SNES Koopa Beach 2",
      "time": "15:09.526709",
      "best_time": "15:09.526709",
      "best_segment": "1:22.862261"
    },
    {
      "title": "N64 Choco Mountain",
      "time": "17:49.769993",
      "best_time": "17:49.769993",
      "best_segment": "2:40.243284"
    },
    {
      "title": "GBA Luigi Circuit",
      "time": "19:57.268599",
      "best_time": "19:57.268599",
      "best_segment": "2:07.498606"
    },
    {
      "title": "GCN Mushroom Bridge",
      "time": "21:43.134619",
      "best_time": "21:43.134619",
      "best_segment": "1:45.866020"
    },
    {
      "title": "SNES Choco Island 2",
      "time": "23:14.581971",
      "best_time": "23:14.581971",
      "best_segment": "1:31.447352"
    },
    {
      "title": "N64 Banshee Boardwalk",
      "time": "25:53.854040",
      "best_time": "25:53.854040",
      "best_segment": "2:39.272069"
    },
    {
      "title": "GBA Sky Garden",
      "time": "27:56.815491",
      "best_time": "27:56.815491",
      "best_segment": "2:02.961451"
    },
    {
      "title": "Yoshi Circuit",
      "time": "30:12.065264",
      "best_time": "30:12.065264",
      "best_segment": "2:15.249773"
    }
  ],
  "theme": "live-split",
  "width": 640,
  "height": 800
}